odoo8_addon_web_tree_dynamic_colored_field-8.0.2.0.0.99.dev9-py2.7-nspkg.pth
odoo8_addon_web_tree_dynamic_colored_field-8.0.2.0.0.99.dev9.dist-info/METADATA
odoo8_addon_web_tree_dynamic_colored_field-8.0.2.0.0.99.dev9.dist-info/RECORD
odoo8_addon_web_tree_dynamic_colored_field-8.0.2.0.0.99.dev9.dist-info/WHEEL
odoo8_addon_web_tree_dynamic_colored_field-8.0.2.0.0.99.dev9.dist-info/namespace_packages.txt
odoo8_addon_web_tree_dynamic_colored_field-8.0.2.0.0.99.dev9.dist-info/top_level.txt
odoo_addons/web_tree_dynamic_colored_field/README.rst
odoo_addons/web_tree_dynamic_colored_field/__init__.py
odoo_addons/web_tree_dynamic_colored_field/__openerp__.py
odoo_addons/web_tree_dynamic_colored_field/i18n/es.po
odoo_addons/web_tree_dynamic_colored_field/i18n/fi.po
odoo_addons/web_tree_dynamic_colored_field/i18n/nl.po
odoo_addons/web_tree_dynamic_colored_field/i18n/sl.po
odoo_addons/web_tree_dynamic_colored_field/i18n/tr.po
odoo_addons/web_tree_dynamic_colored_field/i18n/web_tree_dynamic_colored_field.pot
odoo_addons/web_tree_dynamic_colored_field/static/description/icon.png
odoo_addons/web_tree_dynamic_colored_field/static/src/js/web_tree_dynamic_colored_field.js
odoo_addons/web_tree_dynamic_colored_field/static/src/xml/web_tree_dynamic_colored_field.xml
odoo_addons/web_tree_dynamic_colored_field/views/web_tree_dynamic_colored_field.xml
